nanda_sdk/__init__.py
nanda_sdk/nanda_sdk.py
nanda_sdk/ansible/playbook.yml
nanda_sdk/ansible/templates/internet_of_agents.service.j2
nanda_sdk-0.1.6.dist-info/METADATA
nanda_sdk-0.1.6.dist-info/WHEEL
nanda_sdk-0.1.6.dist-info/entry_points.txt
nanda_sdk-0.1.6.dist-info/top_level.txt
nanda_sdk-0.1.6.dist-info/RECORD
