Metadata-Version: 2.4
Name: nanda_sdk
Version: 0.1.6
Summary: SDK for setting up Internet of Agents servers
Home-page: https://github.com/aidecentralized/nanda-sdk
Author: NANDA
Author-email: admin@nanda-registry.com
Classifier: Programming Language :: Python :: 3
Classifier: License :: OSI Approved :: MIT License
Classifier: Operating System :: POSIX :: Linux
Requires-Python: >=3.6
Requires-Dist: boto3==1.38.24
Requires-Dist: botocore==1.38.24
Requires-Dist: requests==2.31.0
Requires-Dist: pyyaml==6.0.1
Requires-Dist: ansible==8.7.0
Dynamic: author
Dynamic: author-email
Dynamic: classifier
Dynamic: description
Dynamic: description-content-type
Dynamic: home-page
Dynamic: requires-dist
Dynamic: requires-python
Dynamic: summary
